mmcq_numba/__init__.py
mmcq_numba/color.py
mmcq_numba/constant.py
mmcq_numba/math_.py
mmcq_numba/quantize.py
mmcq_numba/region.py
mmcq_numba/struct.py
mmcq_numba-0.1.1.dist-info/LICENSE
mmcq_numba-0.1.1.dist-info/METADATA
mmcq_numba-0.1.1.dist-info/WHEEL
mmcq_numba-0.1.1.dist-info/top_level.txt
mmcq_numba-0.1.1.dist-info/RECORD
