Metadata-Version: 2.1
Name: mmcq-numba
Version: 0.1.1
Summary: Analyze dominant colors in image with MMCQ algorithm
Home-page: https://github.com/hirokic5/mmcq_numba.git
Author: hirokic5
Author-email: kanbac5@gmail.com
License: Apache-2.0 license
Keywords: mmcq dominant-color
License-File: LICENSE
Requires-Dist: numba
